spiro_zscore/__init__.py
spiro_zscore/version.py
spiro_zscore/zscore.py
spiro_zscore/tables/spiro-zscore-lookup.csv
spiro_zscore-0.4.0.dist-info/METADATA
spiro_zscore-0.4.0.dist-info/WHEEL
spiro_zscore-0.4.0.dist-info/top_level.txt
spiro_zscore-0.4.0.dist-info/RECORD
